zensols/lmtask/resources/app.conf
zensols/lmtask/resources/default.conf
zensols/lmtask/resources/llama.yml
zensols/lmtask/resources/obj.yml
zensols/lmtask/resources/quant.yml
zensols/lmtask/resources/tasks.yml
zensols/lmtask/resources/train.yml
zensols/lmtask/resources/prompts/ner.txt
zensols/lmtask/resources/prompts/sentiment.txt
zensols/lmtask/__init__.py
zensols/lmtask/app.py
zensols/lmtask/cli.py
zensols/lmtask/dataset.py
zensols/lmtask/generate.py
zensols/lmtask/hf.py
zensols/lmtask/instruct.py
zensols/lmtask/llama.py
zensols/lmtask/task.py
zensols/lmtask/train.py
zensols_lmtask-0.1.1.dist-info/METADATA
zensols_lmtask-0.1.1.dist-info/WHEEL
zensols_lmtask-0.1.1.dist-info/entry_points.txt
zensols_lmtask-0.1.1.dist-info/licenses/LICENSE.md
zensols_lmtask-0.1.1.dist-info/RECORD
