Metadata-Version: 2.3
Name: zensols_lmtask
Version: 0.1.1
Summary: A large language model (LLM) API to train and inference specifically for tasks.
Project-URL: Homepage, https://github.com/plandes/lmtask
Project-URL: Documentation, https://plandes.github.io/lmtask
Project-URL: Repository, https://github.com/plandes/lmtask.git
Project-URL: Issues, https://github.com/plandes/lmtask/issues
Project-URL: Changelog, https://github.com/plandes/lmtask/blob/master/CHANGELOG.md
Author-email: Paul Landes <landes@mailc.net>
License: MIT
Keywords: tooling
Requires-Python: <3.14,>=3.11
Requires-Dist: accelerate~=1.9.0
Requires-Dist: datasets~=4.0.0
Requires-Dist: jinja2~=3.1
Requires-Dist: partial-json-parser==0.2.1.1.post5
Requires-Dist: peft~=0.17.0
Requires-Dist: torch~=2.7.1
Requires-Dist: transformers~=4.54.1
Requires-Dist: trl==0.20.0
Requires-Dist: zensols-db~=1.4.1
